README.rst
setup.py
flask_nav/__init__.py
flask_nav/elements.py
flask_nav/renderers.py
flask_nav.egg-info/PKG-INFO
flask_nav.egg-info/SOURCES.txt
flask_nav.egg-info/dependency_links.txt
flask_nav.egg-info/requires.txt
flask_nav.egg-info/top_level.txt