Metadata-Version: 1.1
Name: flask-nav
Version: 0.4
Summary: Easily create navigation for Flask applications.
Home-page: http://github.com/mbr/flask-nav
Author: Marc Brinkmann
Author-email: git@marcbrinkmann.de
License: MIT
Platform: UNKNOWN
Classifier: Programming Language :: Python :: 2
Classifier: Programming Language :: Python :: 3
